file_clerk/__init__.py
file_clerk/clerk.py
file_clerk-1.1.14.dist-info/LICENSE.rst
file_clerk-1.1.14.dist-info/METADATA
file_clerk-1.1.14.dist-info/WHEEL
file_clerk-1.1.14.dist-info/RECORD
